{
  "AAPL": {
    "name": "Apple Inc.",
    "price": 200.69,
    "change": -0.16,
    "percent": -0.08
  },
  "MSFT": {
    "name": "Microsoft Corporation",
    "price": 460.76,
    "change": 0.4,
    "percent": 0.09
  },
  "NVDA": {
    "name": "NVIDIA Corporation",
    "price": 137.68,
    "change": 2.55,
    "percent": 1.89
  },
  "GOOGL": {
    "name": "Alphabet Inc.",
    "price": 169.02,
    "change": -2.72,
    "percent": -1.58
  },
  "DE": {
    "name": "Deere & Company",
    "price": 505.54,
    "change": -0.7,
    "percent": -0.14
  },
  "ADM": {
    "name": "Archer-Daniels-Midland Company",
    "price": 47.84,
    "change": -0.43,
    "percent": -0.89
  },
  "BG": {
    "name": "Bunge Limited",
    "price": 78.2,
    "change": 0.03,
    "percent": 0.04
  },
  "CF": {
    "name": "CF Industries Holdings, Inc.",
    "price": 92.68,
    "change": 2.0,
    "percent": 2.21
  }
}